codequest22/__init__.py
codequest22/__main__.py
codequest22/codequest.png
codequest22/__pycache__/__init__.cpython-38.pyc
codequest22/client/__init__.py
codequest22/client/network.py
codequest22/client/runner.py
codequest22/client/__pycache__/__init__.cpython-38.pyc
codequest22/client/__pycache__/network.cpython-38.pyc
codequest22/client/__pycache__/runner.cpython-38.pyc
codequest22/server/__init__.py
codequest22/server/ant.py
codequest22/server/energy.py
codequest22/server/events.py
codequest22/server/global_map.py
codequest22/server/network.py
codequest22/server/replay.py
codequest22/server/requests.py
codequest22/server/summarise_game.py
codequest22/server/maps/central.json
codequest22/server/maps/claustrophobic.json
codequest22/server/maps/cornered.json
codequest22/server/maps/open.json
codequest22/server/maps/small.json
codequest22/stats/__init__.py
codequest22/stats/ants.py
codequest22/stats/energy.py
codequest22/stats/general.py
codequest22/stats/hill.py
codequest22/visual/__init__.py
codequest22/visual/constants.py
codequest22/visual/game.py
codequest22/visual/game_input.py
codequest22/visual/screen.py
codequest22/visual/utils.py
codequest22/visual/fonts/Montserrat/Montserrat-Black.ttf
codequest22/visual/fonts/Montserrat/Montserrat-BlackItalic.ttf
codequest22/visual/fonts/Montserrat/Montserrat-Bold.ttf
codequest22/visual/fonts/Montserrat/Montserrat-BoldItalic.ttf
codequest22/visual/fonts/Montserrat/Montserrat-ExtraBold.ttf
codequest22/visual/fonts/Montserrat/Montserrat-ExtraBoldItalic.ttf
codequest22/visual/fonts/Montserrat/Montserrat-ExtraLight.ttf
codequest22/visual/fonts/Montserrat/Montserrat-ExtraLightItalic.ttf
codequest22/visual/fonts/Montserrat/Montserrat-Italic.ttf
codequest22/visual/fonts/Montserrat/Montserrat-Light.ttf
codequest22/visual/fonts/Montserrat/Montserrat-LightItalic.ttf
codequest22/visual/fonts/Montserrat/Montserrat-Medium.ttf
codequest22/visual/fonts/Montserrat/Montserrat-MediumItalic.ttf
codequest22-1.1.3.dist-info/LICENSE
codequest22-1.1.3.dist-info/METADATA
codequest22-1.1.3.dist-info/WHEEL
codequest22-1.1.3.dist-info/entry_points.txt
codequest22-1.1.3.dist-info/top_level.txt
codequest22-1.1.3.dist-info/RECORD
